{
    "name": "Relativistic flashlight",
    "steps": [{"caption": "A flashlight emits a photon. It moves away at the speed of light. An observer moves past at a high speed. What will the observer see?",
               "objects": [{"object": "extendedObject", "x": [0, 0, 0], 
			    "p": [0, 0, 0], "m": 1, 
			    "shape": [[0, 2, 0, 0], [3, 4, 0, 0], 
				      [3, -4, 0, 0], [0, -2, 0, 0], 
				      [-5, -2, 0, 0], [-5, 2, 0, 0], 
				      [0, 2, 0, 0]]},
                           {"object": "photon", "x": [3, 0, 0], "v": [1, 0, 0]},
                           {"object": "extendedObject", "x": [50, -30, 0], 
			    "p": [-6, 0, 0], "m": 1, 
			    "shape": {"type": "aSphere", "params": [3, 50]}, 
			    "label": "Observer"}
                          ],
               "options": {"showFramePos": true, "showVisualPos": false,
			   "showGamma": false}},
              {"caption": "From the observer's perspective, the photon travels exactly the speed of light &mdash; with the flashlight chasing it! Light moves at the same speed according to all observers.",
               "objects": [{"object": "extendedObject", "x": [0, 0, 0], 
			    "p": [0, 0, 0], "m": 1, 
			    "shape": [[0, 2, 0, 0], [3, 4, 0, 0], 
				      [3, -4, 0, 0], [0, -2, 0, 0],
				      [-5, -2, 0, 0], [-5, 2, 0, 0],
				      [0, 2, 0, 0]]},
                           {"object": "photon", "x": [3, 0, 0], "v": [1, 0, 0]},
                           {"object": "extendedObject", "x": [50, -30, 0], 
			    "p": [-6, 0, 0], "m": 1, 
			    "shape": {"type": "aSphere", "params": [3, 50]},
			    "label": "Observer"}
                          ],
               "options": {"showFramePos": true, "showVisualPos": false, 
			   "showGamma": false},
               "frame": 2,
               "shift": [0, 0, 0, -70]}
             ]
}